Workbook
Name consistency: Lists!$E$2:$E$4
Name quality: Lists!$F$2:$F$4
Name strength: 'Scoring Requirements'!$B$40:$B$43
Name sustainable: Lists!$G$2:$G$4

Sheet Assessment Guidance
B2: Governance Core Assessment
B3: Assessment Guideline
B5: Introduction
C6: This assessment guideline supports both internal self-assessments and external assessments of the Governance Core within the Safety Energy Loop Framework. The guideline is not an assessment tool in itself. It is a supporting resource designed to help assessors understand the intent of the governance criteria, how the elements connect, and how system maturity presents in practice. It is intended to guide professional judgement, not replace it. Assessors are expected to move beyond a traditional audit approach. The most valuable insights will come from conversations, observation, and testing how governance operates under normal conditions and under pressure, rather than relying solely on document review.
B8: Section One | C8: General Assessment Principles
C9: This section outlines the principles that underpin a credible and value-adding governance assessment. These principles apply to all elements of the Governance Core and should be applied consistently, whether the assessment is conducted as a self-review or by an external assessor. The purpose of the assessment is to understand how well the governance system functions, not simply whether components exist. Key principles include: • Assess the system as a whole, not individual documents in isolation. Governance elements are interconnected and should be evaluated in combination. • Focus on how governance influences real decisions, behaviours, and outcomes, particularly for high-risk work. • Use multiple sources of evidence, including documentation, interviews, field observations, and lived experience. • Test alignment between what is described, what is demonstrated, and what is experienced by people at different levels. • Avoid checklist-based scoring. Professional judgement is required to determine maturity based on patterns and consistency. • Seek evidence of intent being translated into action, not just stated expectations. • Look for both strengths and system constraints. The goal is insight and improvement, not compliance confirmation. Assessments should produce outcomes that are accurate, objective, reliable, and genuinely useful to the organisation. Where gaps are identified, assessors should aim to describe why they exist and how they affect system performance.
B11: Section Two | C11: Assessment References
C12: This section provides reference material to help assessors interpret maturity levels and understand how governance maturity presents in practice. Rather than prescribing a fixed list of evidence, this section describes what governance maturity typically looks like, sounds like, and feels like when it is operating effectively as part of an integrated management system. Assessors are encouraged to test what they have observed, reviewed, and experienced against: • Process - the defined relationship and flow between components of the system. • People - the effective integration of human energy in enabling components of the system to be effective and/or interact as designed. • Systems – the formal structures, processes, decision rules, and governance mechanisms in place. • Symbols – what is visibly prioritised, reinforced, and valued across the organisation. • Behaviours – how leaders and workers interact with governance processes in real situations. Where opportunities for improvement are identified, assessors should align observations to the maturity descriptors used in this framework. Language should describe system behaviour and governance effectiveness, rather than individual performance. The examples provided are intended as guidance only. They are not exhaustive, and assessors are expected to apply judgement based on the organisation’s context, risk profile, and operating environment.

Sheet PART A - Governance
A1: Category | B1: Intent and fundamental criteria | C1: Reactive Safety is largely reactive, fragmented and person-dependent, with little shared understanding, inconsistent practices and minimal system coherence. Decisions are primarily driven by production or compliance pressures rather than an articulated view of risk. | D1: Proactive Safety systems are established and broadly understood, but application and influence on decisions are uneven across the organisation. Performance relies on emerging structures and capable leaders rather than a fully embedded, self-sustaining system. | E1: Resilient Safety is fully integrated into how work is designed, decided and delivered, with clear, shared understanding of risk across all levels of the organisation. The system is self-sustaining and continuously improving, with decisions consistently guided by evidence, learning and a long-term view of risk reduction.
A2: LEADERSHIP & ACCOUNTABILITY | B2: Intent: Leadership sets the direction for safety, visibly owns risk, and is accountable for system performance and outcomes, ensuring that safety is consistently prioritised in decisions, behaviours, and resource allocation across the organisation.
B3: 1.1 Leadership Intent and Expectations Leadership clearly defines what safety means for the organisation and translates that intent into consistent expectations for how work is planned and decided. Focus Areas Clarity and consistency of leadership safety intent Translation of intent into roles, expectations and decisions Shared understanding of safety intent across leadership layers Visible alignment between what leaders say and what they do | C3: What it looks like Safety intent exists, but it is expressed as broad values or slogans rather than decision rules. Expectations for leaders and supervisors are implied rather than clearly stated. Different leaders describe safety priorities in different ways. Safety requirements are heavily document-based and feel separate from operational planning. What it sounds like “Safety is important” without being able to define what that means in decisions. “Just follow the procedure” used as the default response to risk issues. “That’s HSE’s job” said directly or indirectly. What it feels like Teams are unsure what leadership expects when risk and production conflict. Safety messaging changes depending on the leader, the site, or the week. Typical activities and routines Safety is discussed, but mostly after something goes wrong or when audits are due. Plans exist, but safety considerations often appear late in planning or only in approval steps. | D3: What it looks like Leadership intent is clearer and more stable, with a shared language that most leaders use consistently. Expectations are written into leader responsibilities and planning routines. Leaders increasingly reference safety intent during planning, approvals, and resourcing discussions. Safety expectations are clearer for supervisors, especially around stop-work and escalation. What it sounds like “Here is how we decide when risk changes” “What is the control that prevents serious harm here” “If we cannot verify the control, we do not proceed” What it feels like People can predict how leaders will respond to high-risk situations. Expectations are clearer, even if execution still varies between areas. Typical activities and routines Leaders routinely participate in risk conversations, not only compliance checks. Planning includes safety considerations earlier, particularly for high-risk work. Leaders test understanding through questions, not just reminders. | E3: What it looks like Leadership intent is operational and decision-based, with clear non-negotiables and clear boundaries. Expectations are consistently applied across teams, sites, and contractors. Safety intent is embedded into planning, work design, and operational decision forums. Leaders model the expected behaviours under pressure, not only in calm conditions. What it sounds like “We are not resourcing this unless we can control the risk” “Stop-work is expected when controls degrade” “Show me the evidence the critical controls are working today” What it feels like Safety is experienced as part of how work is done, not as an overlay. Teams feel clear about what good looks like and what will be supported. Typical activities and routines Leaders proactively use risk information to shape priorities and trade-offs. Leaders coach expectations into practice through observation, feedback, and follow-through. The same intent is visible from executive meetings through to pre-starts and contractor interfaces.
B4: 1.2 Leadership Accountability for Outcomes Leadership is explicitly accountable for safety outcomes and the performance of the safety system, not just compliance or incident rates. Focus Areas Formal accountability for safety in leadership performance measures Ownership of system performance and critical control health Leadership response to incidents, risk and system failures Consistency and fairness in how accountability is applied | C4: What it looks like Accountability exists mainly through lag indicators and compliance checks. Safety performance is measured, but ownership is unclear when system weaknesses are found. Actions are assigned, but follow-through depends on individual leaders. When incidents occur, focus leans toward individual performance rather than system performance. What it sounds like “We need to get our TRIFR down” as the primary measure of success. “We have trained them, so it’s on them now” “We just need people to follow the rules” What it feels like Accountability is inconsistent and can feel reactive or event-driven. People see safety as something leaders talk about, but not always something leaders own. Typical activities and routines Incident reviews occur, but governance changes are rare. Corrective actions are created, but learning is not consistently embedded across teams. | D4: What it looks like Leadership accountability expands beyond injury rates to include system performance elements. Leaders have defined accountabilities for risk, controls, assurance activities, and actions. Performance discussions include leading indicators and the health of controls for serious risks. Incident response increasingly looks at system causes and leadership decisions. What it sounds like “What failed in the system that allowed this” “Which control should have prevented this, and was it verified” “What are we changing at leadership level” What it feels like Accountability feels more structured and fair, though not yet consistent everywhere. Leaders are increasingly expected to own improvement, not delegate it. Typical activities and routines Leaders regularly review action closure, recurring issues, and critical control performance. Leaders are more likely to resource fixes and remove barriers raised by the workforce. | E4: What it looks like Leadership accountability is clearly linked to system performance, risk control, and learning outcomes. Leaders are accountable for the integrity of critical controls and the effectiveness of governance routines. Accountability is consistent across seniority levels and business units. Following serious events, leadership decisions, governance structures, and resourcing are adjusted. What it sounds like “We own this risk and we own the controls” “We will not accept unknown control health” “We will change the way we govern this work, not just update a procedure” What it feels like Accountability is predictable, risk-based, and focused on improvement rather than blame. People trust that raising issues will lead to meaningful action, not punishment or silence. Typical activities and routines Leaders use assurance results, data trends, and learning to make visible changes in priorities and operations. Leaders actively verify control health and systematically address recurring weaknesses. Contractors are held to the same accountability expectations through clear oversight and governance.
A5: DECISION RIGHTS & GOVERNANCE STRUCTURE | B5: Intent: Clear, consistent, and transparent decision-making structures enable timely, risk-informed decisions for high-risk work, ensuring that authority, escalation, and oversight are unambiguous and operate effectively under both routine and pressured conditions.
B6: 2.1 Decision Rights for High-Risk Work Decision rights for high-risk work are clear, consistently applied, and understood across all levels, ensuring timely, risk-informed decisions and effective stop-work authority. Focus Areas Clarity of approval, escalation, and stop-work authority Consistent application of decision rules in practice Alignment between documented decision rights and real decisions Functionality of escalation pathways under pressure | C6: What it looks like Decision rules for high-risk work exist in some documents, but they are scattered, incomplete, or not well understood. Different leaders give different answers about who can approve, escalate, or stop work. Stop-work authority exists in policy but is rarely exercised in practice. Approvals are often driven by urgency, relationships, or hierarchy rather than clear criteria. What it sounds like “Check with your supervisor.” “Just get sign-off and keep moving.” “We can sort the paperwork later.” “It depends who you ask.” What it feels like People are uncertain about their authority under pressure. Workers hesitate to stop work unless explicitly told to. Decisions can feel personalised rather than system-based. Typical activities and routines High-risk permits or approvals exist but are treated as administrative steps. Escalation happens inconsistently and often only after something goes wrong. Decision making is reactive rather than planned. | D6: What it looks like A formal Decision Rights Matrix or equivalent exists and is reasonably well understood. Roles for approval, escalation, and stop-work are clearer, particularly for high-risk tasks. Most leaders follow the agreed decision pathways, especially for major risks. There is growing recognition that escalation is legitimate rather than a failure. What it sounds like “Who is the approver for this level of risk?” “Let’s escalate before we proceed.” “We need to verify the controls before we move forward.” “That decision sits with [role], not with us.” What it feels like People are more confident about who decides what. Stopping work is becoming more acceptable, though still uneven. Decision making feels more structured, even if not yet flawless. Typical activities and routines High-risk approvals generally follow a defined pathway. Leaders increasingly reference decision rules in meetings and planning. Escalation occurs more often, though sometimes still late or under pressure. | E6: What it looks like Decision rights are clearly defined, widely understood, and consistently applied across sites and contractors. Stop-work authority is genuinely embedded and used as a normal part of operations when controls degrade. Escalation pathways function effectively even under schedule or commercial pressure. Decision rights are stress-tested and refined based on real experience. What it sounds like “This exceeds our threshold, so we escalate.” “We will pause until the right approver reviews this.” “If we can’t verify the control, we don’t proceed.” “Let’s review whether our decision rules still make sense.” What it feels like People trust the system and know exactly what to do when risk changes. Stopping work is seen as responsible, not disruptive. Decisions feel predictable, fair, and risk-based rather than political. Typical activities and routines Leaders actively coach decision rights in real situations. Escalation happens early, not at crisis point. Decision rules are periodically reviewed and improved based on lessons learned.
B7: 2.2 Governance Forums and Structure A clear and effective governance structure enables purposeful safety decision-making, oversight, and accountability across the organisation. Focus Areas Clarity of governance structure, roles, and forums Quality and purposefulness of safety meetings and reviews Decision-making, action tracking, and follow-through Flow of safety information between frontline and leadership | C7: What it looks like Safety meetings and forums exist but are inconsistent in purpose or quality. Agendas tend to focus on incidents, compliance, or reporting rather than real risk. Actions are recorded, but closure is uneven and follow-up is weak. Frontline information rarely meaningfully shapes leadership discussions. What it sounds like “We need to get through the agenda.” “Let’s just note that for next time.” “We’ll take that offline.” “Same issues again this month.” What it feels like Meetings feel routine rather than valuable. Workers are unsure whether raising issues will lead to change. Governance feels like a reporting exercise rather than decision-making. Typical activities and routines Regular meetings occur but vary widely between sites or teams. Safety is discussed, but rarely changes priorities or resourcing. Information tends to flow upward slowly or not at all. | D7: What it looks like Governance structure is clearer, with defined forums, roles, and cadence. Safety meetings increasingly focus on high-risk activities, controls, and trends. Actions are more consistently tracked and closed. There is growing visibility of frontline issues at leadership level. What it sounds like “What are our top risks this month?” “Which actions are still open, and why?” “What is this telling us about our system?” “We need to hear from the site on this.” What it feels like Meetings feel more purposeful and less like a formality. Leaders appear more engaged with real safety issues. Workers begin to see that their concerns can influence decisions. Typical activities and routines Standing agendas include risk, controls, and learning rather than only incidents. Leadership forums review trends and recurring issues, not just one-off events. Action tracking becomes more visible and disciplined. | E7: What it looks like Governance structure is clearly defined, understood, and consistently applied across the organisation. Safety forums actively shape strategy, priorities, and resourcing. Decisions are transparent, well documented, and clearly linked to risk information. Information flows smoothly between frontline, supervisors, and executives in both directions. What it sounds like “Based on this trend, we need to change our approach.” “We will allocate resources to address this systemic issue.” “What are we hearing from the field that we need to act on?” “Let’s close the loop and communicate the outcome.” What it feels like Governance feels alive rather than bureaucratic. People trust that raising issues will lead to meaningful action. Safety decision-making feels integrated with how the business runs. Typical activities and routines Leaders routinely use governance forums to make real risk-based decisions. Frontline insights directly influence leadership priorities. Governance processes are reviewed and refined based on effectiveness, not just compliance.
A8: LEGAL & RISK GOVERNANCE | B8: Intent: Legal duties and risk boundaries are systematically translated into practical controls and decision rules, ensuring that governance is defensible, consistent, and aligned to the organisation’s tolerance for risk.
B9: 3.1 Translation of Legal Duties Legal duties are systematically translated into practical controls and accountabilities so governance is defensible and operationally meaningful. Focus Areas Currency and relevance of the legal register Clear mapping of legal duties to controls and roles Use of legal requirements in risk assessments and procedures Systematic updates when laws or standards change | C9: What it looks like A legal register exists, but it is treated as a compliance artefact rather than an operational tool. Legal duties are listed, but not clearly connected to real controls, procedures, or accountable roles. Risk assessments and procedures reference legislation inconsistently, if at all. Updates to legal requirements tend to be reactive, often triggered by audits or incidents. What it sounds like “We have a legal register somewhere.” “That’s covered in the procedure.” “HSE will look after the legal stuff.” “We’ll update it when we get audited.” What it feels like Legal compliance feels separate from how work is actually done. Teams experience legal requirements as paperwork rather than as risk controls. Leaders see legal compliance as HSE’s responsibility, not a shared governance duty. Typical activities and routines The legal register is reviewed irregularly or only when required. Procedures exist, but their connection to legal duties is not obvious to users. Risk assessments are often generic and not clearly grounded in legal obligations. | D9: What it looks like The legal register is current and more clearly structured, with visible links to key controls. Legal duties are increasingly mapped to specific procedures and accountable roles. Risk assessments more regularly reference relevant legal requirements, especially for high-risk work. Changes in law or standards trigger updates to some procedures or controls, though not always systematically. What it sounds like “Which legal duty relates to this control?” “We need to update that procedure because the standard changed.” “Who owns compliance for this requirement?” “Let’s check if our controls still meet the regulation.” What it feels like Legal requirements begin to feel more relevant to operational decision-making. Leaders are more aware that legal duties shape risk controls, not just paperwork. Compliance feels more structured, though still uneven across the business. Typical activities and routines Legal register reviews are scheduled and involve relevant functions, not only HSE. Some procedures explicitly reference applicable legal duties. High-risk work planning more consistently considers legal requirements. | E9: What it looks like The legal register is a live governance tool that clearly maps duties to critical controls, procedures, and accountable roles. Legal compliance actively informs risk priorities, control design, and decision-making. Changes in legislation or standards automatically trigger systematic reviews of controls, procedures, and training. Legal translation is consistent across sites, projects, and contractors. What it sounds like “This control exists because of this specific legal duty.” “Before we change this process, we need to confirm legal implications.” “Our governance needs to evolve with the new standard.” “Show me how this meets our legal obligations in practice.” What it feels like Legal duties are experienced as part of how safe work is designed, not as external pressure. Teams understand why controls exist, not just how to follow them. Leaders treat legal compliance as a core governance responsibility, not a box-ticking exercise. Typical activities and routines Legal changes trigger structured reviews of risk assessments, controls, and training. Legal mapping is visible in procedures, permits, and critical control documentation. Assurance activities routinely test whether legal duties are being met in practice, not just on paper.
B10: 3.2 Risk Appetite and Decision Boundaries Clear and shared risk boundaries guide consistent, defensible decision-making for routine and high-risk work. Focus Areas Existence and clarity of a documented risk appetite Consistent application of risk boundaries in decisions Alignment between risk appetite, approvals, and planning Leadership intervention when risk boundaries are approached | C10: What it looks like Risk appetite is informal, implicit, or described in vague terms. Leaders often make decisions based on experience, urgency, or commercial pressure rather than clear boundaries. Similar risks may be treated differently depending on who is involved. Risk acceptance is rarely documented in a structured or transparent way. What it sounds like “We just have to get the job done.” “We’ve always done it this way.” “It depends on the situation.” “We’ll manage it as we go.” What it feels like Risk tolerance feels inconsistent and unpredictable. Workers are unsure where the organisation’s true boundaries lie. Decisions can feel personality-driven rather than principle-driven. Typical activities and routines Risk assessments are completed, but thresholds for acceptance are unclear. Approvals are often negotiated rather than based on defined criteria. There is little visible link between risk decisions and any formal risk appetite. | D10: What it looks like A documented risk appetite exists, though it may still be high-level. Leaders increasingly reference risk boundaries in planning and approvals. There is more consistency in how similar risks are treated, particularly for high-risk work. Risk acceptance is more often documented, but rationale may still vary. What it sounds like “Does this fall within our risk appetite?” “We need to justify why we’re accepting this risk.” “This is above our threshold, so we need escalation.” “Let’s check if this aligns with our risk boundaries.” What it feels like Decision-making feels more structured and less arbitrary. Teams have a clearer sense of what risks are unacceptable. Leaders are more proactive in questioning risky situations. Typical activities and routines Risk appetite is referenced in key governance forums and approvals. High-risk work planning more consistently considers defined thresholds. Leaders increasingly intervene when risks approach boundaries. | E10: What it looks like Risk appetite is clearly defined, operationalised, and embedded in decision-making across the organisation. Approvals, planning, and resource allocation consistently reflect agreed risk boundaries. Leaders proactively intervene when risks approach or exceed thresholds. The organisation can clearly and confidently justify high-risk decisions to regulators, clients, or stakeholders. What it sounds like “This exceeds our risk appetite, so we will not proceed.” “We need to redesign the work to bring this within our boundaries.” “Our risk appetite guides how we prioritise and resource this.” “Here is why this decision is defensible.” What it feels like Risk decisions feel principled, consistent, and transparent. Workers trust that the organisation will not knowingly accept unacceptable risk. Leaders are visibly committed to staying within defined boundaries, even under pressure. Typical activities and routines Risk appetite is integrated into procedures, permits, and decision rights. Leaders routinely discuss risk boundaries in planning and governance forums. When boundaries are challenged, work is paused, redesigned, or resourced differently rather than pushed through.
A11: ESCALATION, PSYCHOLOGICAL SAFETY & LEARNING INTO GOVERNANCE | B11: Intent: The organisation actively encourages and protects upward flow of risk information, fosters psychological safety, and ensures that learning from incidents, near misses, and operational experience meaningfully reshapes leadership decisions and system design.
B12: 4.1 Escalation Pathways and Speak-Up Clear, trusted, and accessible escalation pathways enable anyone to raise safety concerns without fear and with timely response. Focus Areas Clarity and accessibility of speak-up and escalation routes Defined response timeframes and feedback loops Protection from retaliation when concerns are raised Evidence that issues raised lead to visible action | C12: What it looks like A formal speak-up or escalation process exists on paper, but awareness and use are patchy. Different teams rely on different informal routes to raise concerns. Timeframes for response are unclear or inconsistently applied. Issues are sometimes logged but outcomes are not always visible to those who raised them. What it sounds like “Just tell your supervisor.” “We’ll look into it.” “That’s probably for HSE to handle.” “We don’t want to make a big deal out of it.” What it feels like People are unsure whether raising concerns will lead to anything meaningful. Speaking up can feel risky or dependent on who your leader is. There is a sense that escalation is tolerated rather than encouraged. Typical activities and routines Concerns are raised inconsistently and often only when risk is obvious. Follow-up communication to reporters is sporadic. Escalation tends to happen after problems escalate rather than early. | D12: What it looks like Clear escalation routes are defined and generally understood across most teams. Response timeframes exist and are more consistently applied. There is visible action following some escalations, particularly for high-risk issues. Leaders increasingly treat escalation as legitimate rather than problematic. What it sounds like “If you’re unsure, escalate it.” “Let’s raise this before it gets worse.” “We’ll close the loop with you once we’ve reviewed it.” “Thanks for bringing that forward.” What it feels like People are more confident that raising concerns will lead to action. Speaking up is becoming more normal, though still uneven across areas. There is growing trust in formal escalation pathways. Typical activities and routines Issues are escalated earlier, particularly for high-risk work. Leaders provide more frequent feedback on actions taken. Formal channels (hotlines, reporting systems, or forums) are used alongside face-to-face escalation. | E12: What it looks like Escalation pathways are clear, widely understood, and consistently used across employees and contractors. Defined response timeframes are met as a norm, not an exception. People who raise concerns consistently receive timely feedback and see visible outcomes. Retaliation is actively prevented and addressed if it occurs. What it sounds like “We want to hear about this early.” “Thank you for raising that — here’s what we’re doing.” “If you’re uncomfortable, use the formal channel.” “We will pause until this is resolved.” What it feels like Speaking up feels safe, expected, and valued. Escalation is seen as a sign of a strong system, not a failure. People trust that concerns will be taken seriously regardless of seniority. Typical activities and routines Leaders actively invite escalation and check for concerns in the field. Feedback loops are systematic and visible. Patterns in escalations are reviewed at governance forums to prevent recurrence.
B13: 4.2 Psychological Safety Leaders create conditions where people feel safe to surface risk, challenge decisions, and speak openly about problems. Focus Areas Leadership behaviours that invite challenge and bad news Quality of dialogue in meetings and decision forums Absence of blame and fear of consequences for speaking up Evidence that constructive dissent is valued and acted upon | C13: What it looks like Overt fear is uncommon, but people are cautious about challenging decisions. Meetings are polite but often avoid difficult or uncomfortable topics. Dissent tends to be indirect or raised privately rather than openly. Blame still surfaces after incidents, even if unintentionally. What it sounds like “Let’s not rock the boat.” “We’ll take that offline.” “We should be careful how we phrase this.” Silence when tough questions are asked. What it feels like People are comfortable raising minor issues but hesitant to surface serious concerns. There is an unspoken sense that speaking up could have consequences. Safety conversations feel somewhat controlled rather than open. Typical activities and routines Leaders ask for input, but mainly from the same confident voices. Meetings focus more on reporting than real discussion of risk. Challenging topics are often deferred rather than explored. | D13: What it looks like Leaders more actively invite challenge and bad news in meetings. Constructive dissent is increasingly visible and tolerated. People are more willing to speak up about risk, especially when prompted. Blame is reducing, though not yet eliminated. What it sounds like “What are we missing here?” “I’d like to hear a different perspective.” “Let’s talk openly about what could go wrong.” “We’re not here to point fingers.” What it feels like People are more confident that they can speak up without negative consequences. Discussions feel more genuine, though still inconsistent across leaders. There is growing trust that concerns will be heard. Typical activities and routines Leaders consciously create space for discussion in meetings. Workers increasingly raise risks earlier rather than waiting. Leaders model vulnerability by acknowledging uncertainty or mistakes. | E13: What it looks like Healthy debate and constructive challenge are routine across all levels. Leaders actively seek out dissenting views, especially on high-risk decisions. People feel safe raising uncomfortable truths, even about leadership decisions. Blame is consistently replaced with system thinking. What it sounds like “Who disagrees, and why?” “What risks are we not seeing?” “Thank you for challenging that.” “Let’s focus on how the system failed, not who.” What it feels like Psychological safety is deeply embedded, not leader-dependent. Speaking up feels normal, expected, and valued. People trust that honesty will lead to improvement, not punishment. Typical activities and routines Leaders publicly acknowledge and reward people who surface risk early. Difficult conversations occur openly and constructively. Teams routinely reflect on how they handle dissent and improve their dialogue.
B14: 4.3 Learning Feeding Back into Governance Insights from incidents, near misses, and operational experience actively reshape leadership decisions and system design. Focus Areas Quality and depth of incident investigations Evidence that learning leads to system or governance changes Sharing of lessons beyond the immediate site or team Continuous refinement of decision rules, controls, or structures | C14: What it looks like Serious incidents are investigated, but learning often remains local. Corrective actions tend to focus on immediate fixes rather than systemic issues. Governance structures or decision rules rarely change as a result of incidents. Lessons learned are inconsistently shared across sites or teams. What it sounds like “We need to close out these actions.” “Let’s update the procedure.” “This was a one-off.” “We’ll remind people to be careful.” What it feels like Learning feels reactive rather than proactive. Teams may repeat similar issues in different areas. Investigations can feel like compliance exercises rather than opportunities to improve. Typical activities and routines Investigations focus heavily on proximate causes. Actions are tracked but not always evaluated for effectiveness. Knowledge sharing is ad hoc and depends on individuals. | D14: What it looks like Investigations increasingly identify systemic contributors, not just immediate causes. Learning more regularly leads to updates in procedures, controls, or training. Lessons learned are shared beyond the immediate site or team. Some leadership-level changes occur following significant events. What it sounds like “What does this tell us about our system?” “We need to change how we manage this risk.” “Let’s share this with other sites.” “What can we do differently next time?” What it feels like There is growing recognition that incidents reveal system weaknesses. Learning is becoming more purposeful, though still uneven. People see some tangible improvements after events. Typical activities and routines Cross-site learning forums or bulletins are used more regularly. Leaders are more involved in reviewing investigation findings. Controls or decision rules are occasionally revised based on learning. | E14: What it looks like Investigations consistently examine leadership decisions, governance structures, and system design. Learning routinely drives changes to governance, decision rules, or critical controls. Lessons are systematically shared, embedded, and verified across the organisation. The system visibly evolves over time based on real operational experience. What it sounds like “What do we need to change in how we govern this work?” “This event shows our decision rules need refinement.” “Let’s update our risk boundaries based on this learning.” “How will we verify that this change actually reduces risk?” What it feels like Learning feels continuous, not event-driven. People trust that incidents lead to meaningful system improvement. The organisation feels more resilient over time, not just reactive. Typical activities and routines Leadership reviews regularly translate investigation insights into governance changes. Decision rights, controls, and risk appetite are refined based on evidence. Assurance activities test whether lessons have been effectively embedded.

Sheet Scoring Worksheet
B2: Governance Core Assessment
B3: Scoring Worksheet
B5: Organisation
B6: Facility/ Asset | H6: Team (if required)
B7: Assessor Name/s | H7: Assessment Date
B10: Category | C10: Intent and fundamental criteria | F10: Strength | H10: Scoring Indicators | L10: Self-Assessment or Baseline
C11: # | D11: Topic | E11: Clauses | F11: Indicators | G11: Don't Touch | H11: Consistent | I11: Quality | J11: Sustained | K11: Don't Touch | L11: Score | M11: Comments / Recommendations
B12: LEADERSHIP & ACCOUNTABILITY | C12: 1.1 | D12: Leadership Intent and Expectations | E12: Clarity and consistency of leadership safety intent | F12: Reactive | G12: =IF(F12="Reactive","R",IF(F12="Proactive","P",IF(F12="Resilient","RE",""))) -> R | H12: C | I12: Q | J12: S | K12: =G12&H12&I12&J12 -> RCQS | L12: =VLOOKUP(K12,Lists!B:C,2,FALSE) -> 3
E13: Translation of intent into roles, expectations and decisions | F13: Resilient | G13: =IF(F13="Reactive","R",IF(F13="Proactive","P",IF(F13="Resilient","RE",""))) -> RE | H13: C | I13: X | J13: X | K13: =G13&H13&I13&J13 -> RECXX | L13: =IFERROR(VLOOKUP(K13,Lists!B:C,2,FALSE),"") -> 7
E14: Shared understanding of safety intent across leadership layers | G14: =IF(F14="Reactive","R",IF(F14="Proactive","P",IF(F14="Resilient","RE",""))) | K14: =G14&H14&I14&J14 | L14: =IFERROR(VLOOKUP(K14,Lists!B:C,2,FALSE),"")
E15: Visible alignment between what leaders say and what they do | G15: =IF(F15="Reactive","R",IF(F15="Proactive","P",IF(F15="Resilient","RE",""))) | K15: =G15&H15&I15&J15 | L15: =IFERROR(VLOOKUP(K15,Lists!B:C,2,FALSE),"")
C16: 1.2 | D16: Leadership Accountability for Outcomes | E16: Formal accountability for safety in leadership performance measures | G16: =IF(F16="Reactive","R",IF(F16="Proactive","P",IF(F16="Resilient","RE",""))) | K16: =G16&H16&I16&J16 | L16: =IFERROR(VLOOKUP(K16,Lists!B:C,2,FALSE),"")
E17: Ownership of system performance and critical control health | G17: =IF(F17="Reactive","R",IF(F17="Proactive","P",IF(F17="Resilient","RE",""))) | K17: =G17&H17&I17&J17 | L17: =IFERROR(VLOOKUP(K17,Lists!B:C,2,FALSE),"")
E18: Leadership response to incidents, risk and system failures | G18: =IF(F18="Reactive","R",IF(F18="Proactive","P",IF(F18="Resilient","RE",""))) | K18: =G18&H18&I18&J18 | L18: =IFERROR(VLOOKUP(K18,Lists!B:C,2,FALSE),"")
E19: Consistency and fairness in how accountability is applied | G19: =IF(F19="Reactive","R",IF(F19="Proactive","P",IF(F19="Resilient","RE",""))) | K19: =G19&H19&I19&J19 | L19: =IFERROR(VLOOKUP(K19,Lists!B:C,2,FALSE),"")
B20: DECISION RIGHTS & GOVERNANCE STRUCTURE | C20: 2.1 | D20: Decision Rights for High-Risk Work | E20: Clarity of approval, escalation, and stop-work authority | G20: =IF(F20="Reactive","R",IF(F20="Proactive","P",IF(F20="Resilient","RE",""))) | K20: =G20&H20&I20&J20 | L20: =IFERROR(VLOOKUP(K20,Lists!B:C,2,FALSE),"")
E21: Consistent application of decision rules in practice | G21: =IF(F21="Reactive","R",IF(F21="Proactive","P",IF(F21="Resilient","RE",""))) | K21: =G21&H21&I21&J21 | L21: =IFERROR(VLOOKUP(K21,Lists!B:C,2,FALSE),"")
E22: Alignment between documented decision rights and real decisions | G22: =IF(F22="Reactive","R",IF(F22="Proactive","P",IF(F22="Resilient","RE",""))) | K22: =G22&H22&I22&J22 | L22: =IFERROR(VLOOKUP(K22,Lists!B:C,2,FALSE),"")
E23: Functionality of escalation pathways under pressure | G23: =IF(F23="Reactive","R",IF(F23="Proactive","P",IF(F23="Resilient","RE",""))) | K23: =G23&H23&I23&J23 | L23: =IFERROR(VLOOKUP(K23,Lists!B:C,2,FALSE),"")
C24: 2.2 | D24: Decision Rights for High-Risk Work | E24: Clarity of governance structure, roles, and forums | G24: =IF(F24="Reactive","R",IF(F24="Proactive","P",IF(F24="Resilient","RE",""))) | K24: =G24&H24&I24&J24 | L24: =IFERROR(VLOOKUP(K24,Lists!B:C,2,FALSE),"")
E25: Quality and purposefulness of safety meetings and reviews | G25: =IF(F25="Reactive","R",IF(F25="Proactive","P",IF(F25="Resilient","RE",""))) | K25: =G25&H25&I25&J25 | L25: =IFERROR(VLOOKUP(K25,Lists!B:C,2,FALSE),"")
E26: Decision-making, action tracking, and follow-through | G26: =IF(F26="Reactive","R",IF(F26="Proactive","P",IF(F26="Resilient","RE",""))) | K26: =G26&H26&I26&J26 | L26: =IFERROR(VLOOKUP(K26,Lists!B:C,2,FALSE),"")
E27: Flow of safety information between frontline and leadership | G27: =IF(F27="Reactive","R",IF(F27="Proactive","P",IF(F27="Resilient","RE",""))) | K27: =G27&H27&I27&J27 | L27: =IFERROR(VLOOKUP(K27,Lists!B:C,2,FALSE),"")
B28: LEGAL & RISK GOVERNANCE | C28: 3.1 | D28: Translation of Legal Duties | E28: Currency and relevance of the legal register | G28: =IF(F28="Reactive","R",IF(F28="Proactive","P",IF(F28="Resilient","RE",""))) | K28: =G28&H28&I28&J28 | L28: =IFERROR(VLOOKUP(K28,Lists!B:C,2,FALSE),"")
E29: Clear mapping of legal duties to controls and roles | G29: =IF(F29="Reactive","R",IF(F29="Proactive","P",IF(F29="Resilient","RE",""))) | K29: =G29&H29&I29&J29 | L29: =IFERROR(VLOOKUP(K29,Lists!B:C,2,FALSE),"")
E30: Use of legal requirements in risk assessments and procedures | G30: =IF(F30="Reactive","R",IF(F30="Proactive","P",IF(F30="Resilient","RE",""))) | K30: =G30&H30&I30&J30 | L30: =IFERROR(VLOOKUP(K30,Lists!B:C,2,FALSE),"")
E31: Systematic updates when laws or standards change | G31: =IF(F31="Reactive","R",IF(F31="Proactive","P",IF(F31="Resilient","RE",""))) | K31: =G31&H31&I31&J31 | L31: =IFERROR(VLOOKUP(K31,Lists!B:C,2,FALSE),"")
C32: 3.2 | D32: Risk Appetite and Decision Boundaries | E32: Existence and clarity of a documented risk appetite | G32: =IF(F32="Reactive","R",IF(F32="Proactive","P",IF(F32="Resilient","RE",""))) | K32: =G32&H32&I32&J32 | L32: =IFERROR(VLOOKUP(K32,Lists!B:C,2,FALSE),"")
E33: Consistent application of risk boundaries in decisions | G33: =IF(F33="Reactive","R",IF(F33="Proactive","P",IF(F33="Resilient","RE",""))) | K33: =G33&H33&I33&J33 | L33: =IFERROR(VLOOKUP(K33,Lists!B:C,2,FALSE),"")
E34: Alignment between risk appetite, approvals, and planning | G34: =IF(F34="Reactive","R",IF(F34="Proactive","P",IF(F34="Resilient","RE",""))) | K34: =G34&H34&I34&J34 | L34: =IFERROR(VLOOKUP(K34,Lists!B:C,2,FALSE),"")
E35: Leadership intervention when risk boundaries are approached | G35: =IF(F35="Reactive","R",IF(F35="Proactive","P",IF(F35="Resilient","RE",""))) | K35: =G35&H35&I35&J35 | L35: =IFERROR(VLOOKUP(K35,Lists!B:C,2,FALSE),"")
B36: ESCALATION, PSYCHOLOGICAL SAFETY & LEARNING INTO GOVERNANCE | C36: 4.1 | D36: Escalation Pathways and Speak-Up | E36: Clarity and accessibility of speak-up and escalation routes | G36: =IF(F36="Reactive","R",IF(F36="Proactive","P",IF(F36="Resilient","RE",""))) | K36: =G36&H36&I36&J36 | L36: =IFERROR(VLOOKUP(K36,Lists!B:C,2,FALSE),"")
E37: Defined response timeframes and feedback loops | G37: =IF(F37="Reactive","R",IF(F37="Proactive","P",IF(F37="Resilient","RE",""))) | K37: =G37&H37&I37&J37 | L37: =IFERROR(VLOOKUP(K37,Lists!B:C,2,FALSE),"")
E38: Protection from retaliation when concerns are raised | G38: =IF(F38="Reactive","R",IF(F38="Proactive","P",IF(F38="Resilient","RE",""))) | K38: =G38&H38&I38&J38 | L38: =IFERROR(VLOOKUP(K38,Lists!B:C,2,FALSE),"")
E39: Evidence that issues raised lead to visible action | G39: =IF(F39="Reactive","R",IF(F39="Proactive","P",IF(F39="Resilient","RE",""))) | K39: =G39&H39&I39&J39 | L39: =IFERROR(VLOOKUP(K39,Lists!B:C,2,FALSE),"")
C40: 4.2 | D40: Psychological Safety | E40: Leadership behaviours that invite challenge and bad news | G40: =IF(F40="Reactive","R",IF(F40="Proactive","P",IF(F40="Resilient","RE",""))) | K40: =G40&H40&I40&J40 | L40: =IFERROR(VLOOKUP(K40,Lists!B:C,2,FALSE),"")
E41: Quality of dialogue in meetings and decision forums | G41: =IF(F41="Reactive","R",IF(F41="Proactive","P",IF(F41="Resilient","RE",""))) | K41: =G41&H41&I41&J41 | L41: =IFERROR(VLOOKUP(K41,Lists!B:C,2,FALSE),"")
E42: Absence of blame and fear of consequences for speaking up | G42: =IF(F42="Reactive","R",IF(F42="Proactive","P",IF(F42="Resilient","RE",""))) | K42: =G42&H42&I42&J42 | L42: =IFERROR(VLOOKUP(K42,Lists!B:C,2,FALSE),"")
E43: Evidence that constructive dissent is valued and acted upon | G43: =IF(F43="Reactive","R",IF(F43="Proactive","P",IF(F43="Resilient","RE",""))) | K43: =G43&H43&I43&J43 | L43: =IFERROR(VLOOKUP(K43,Lists!B:C,2,FALSE),"")
C44: 4.3 | D44: Learning Feeding Back into Governance | E44: Quality and depth of incident investigations | G44: =IF(F44="Reactive","R",IF(F44="Proactive","P",IF(F44="Resilient","RE",""))) | K44: =G44&H44&I44&J44 | L44: =IFERROR(VLOOKUP(K44,Lists!B:C,2,FALSE),"")
E45: Evidence that learning leads to system or governance changes | G45: =IF(F45="Reactive","R",IF(F45="Proactive","P",IF(F45="Resilient","RE",""))) | K45: =G45&H45&I45&J45 | L45: =IFERROR(VLOOKUP(K45,Lists!B:C,2,FALSE),"")
E46: Sharing of lessons beyond the immediate site or team | G46: =IF(F46="Reactive","R",IF(F46="Proactive","P",IF(F46="Resilient","RE",""))) | K46: =G46&H46&I46&J46 | L46: =IFERROR(VLOOKUP(K46,Lists!B:C,2,FALSE),"")
E47: Continuous refinement of decision rules, controls, or structures | G47: =IF(F47="Reactive","R",IF(F47="Proactive","P",IF(F47="Resilient","RE",""))) | K47: =G47&H47&I47&J47 | L47: =IFERROR(VLOOKUP(K47,Lists!B:C,2,FALSE),"")
B49: Overall site safety maturity | D49: Average maturity score | H49: Consistent | I49: Quality | J49: Sustained | L49: Ave Score | M49: Notes
B50: Category average | D50: LEADERSHIP & ACCOUNTABILITY | H50: =COUNTIF(H12:H19,"C") -> 2 | I50: =COUNTIF(I12:I19,"Q") -> 1 | J50: =COUNTIF(J12:J19,"S") -> 1 | L50: =AVERAGE(L12:L19) -> 5
D51: DECISION RIGHTS & GOVERNANCE STRUCTURE | H51: =COUNTIF(H20:H27,"C") -> 0 | I51: =COUNTIF(I20:I27,"Q") -> 0 | J51: =COUNTIF(J20:J27,"S") -> 0 | L51: =AVERAGE(L20:L27) -> #DIV/0!
D52: LEGAL & RISK GOVERNANCE | H52: =COUNTIF(H28:H35,"C") -> 0 | I52: =COUNTIF(I28:I35,"Q") -> 0 | J52: =COUNTIF(J28:J35,"S") -> 0 | L52: =AVERAGE(L28:L35) -> #DIV/0!
D53: ESCALATION, PSYCHOLOGICAL SAFETY & LEARNING INTO GOVERNANCE | H53: =COUNTIF(H36:H47,"C") -> 0 | I53: =COUNTIF(I36:I47,"Q") -> 0 | J53: =COUNTIF(J36:J47,"S") -> 0 | L53: =AVERAGE(L36:L47) -> #DIV/0!
D54: # criteria incomplete for lowest maturity level | H54: =COUNTIF(H12:H47,"X") -> 0 | I54: =COUNTIF(I12:I47,"X") -> 1 | J54: =COUNTIF(J12:J47,"X") -> 1 | L54: =AVERAGE(L50:L53) -> #DIV/0!

Sheet Intent Statement
A1: Category | B1: Intent and fundamental criteria | C1: Reactive | D1: Proactive | E1: Resilient
A2: LEADERSHIP & ACCOUNTABILITY | B2: Intent: Leadership sets the direction for safety, visibly owns risk, and is accountable for system performance and outcomes, ensuring that safety is consistently prioritised in decisions, behaviours, and resource allocation across the organisation. 1.1 Leadership Intent and Expectations Clarity and consistency of leadership safety intent Translation of intent into roles, expectations and decisions Shared understanding of safety intent across leadership layers Visible alignment between what leaders say and what they do 1.2 Leadership Accountability for Outcomes Formal accountability for safety in leadership performance measures Ownership of system performance and critical control health Leadership response to incidents, risk and system failures Consistency and fairness in how accountability is applied | C2: There is a visible commitment to safety, but intent is often expressed as broad values rather than clear decision rules. | D2: Leaders are broadly aligned in their safety messaging, and intent is increasingly translated into expectations for how work is planned and decided. | E2: Leadership intent is operational, consistent, and actively shapes strategy, resourcing, and risk trade-offs.
C3: Safety expectations exist, but application varies across leaders, teams, and sites. | D3: Most leaders understand and reference safety intent, particularly for high-risk work. | E3: Safety expectations are consistently applied across all layers of the organisation, including contractors.
C4: Accountability is primarily tied to compliance and lagging metrics. | D4: Leaders are increasingly accountable for system performance and critical control health. | E4: Leaders visibly own the health of the safety system and are accountable for learning, control effectiveness, and governance outcomes.
C5: When things go wrong, responses tend to focus on individuals rather than the system. | D5: Incident responses more often examine system contributors and leadership decisions. | E5: After significant events, leadership decisions, governance structures, and resourcing are routinely adjusted.
C6: Safety is still largely leader dependent. | D6: Ownership of safety is growing beyond formal leadership roles. | E6: Safety is owned across the organisation, with leaders modelling the expected behaviours under pressure.
A7: DECISION RIGHTS & GOVERNANCE STRUCTURE | B7: Intent: Clear, consistent, and transparent decision-making structures enable timely, risk-informed decisions for high-risk work, ensuring that authority, escalation, and oversight are unambiguous and operate effectively under both routine and pressured conditions. 2.1 Decision Rights for High-Risk Work Clarity of approval, escalation, and stop-work authority Consistent application of decision rules in practice Alignment between documented decision rights and real decisions Functionality of escalation pathways under pressure 2.2 Governance Forums and Structure Clarity of governance structure, roles, and forums Quality and purposefulness of safety meetings and reviews Decision-making, action tracking, and follow-through Flow of safety information between frontline and leadership | C7: Decision rules for high-risk work exist, but are not consistently understood or applied. | D7: A formal decision rights structure exists and is generally understood across leadership layers. | E7: Decision rights are clear, widely understood, and consistently applied across sites and contractors.
C8: Stop-work authority exists in policy, but is rarely exercised in practice. | D8: Stop-work is becoming more acceptable, particularly for clearly high-risk situations. | E8: Stopping work is normalised when controls are uncertain or degraded.
C9: Governance forums operate, but often feel like reporting exercises rather than decision-making spaces. | D9: Safety forums are more purposeful and increasingly focused on risk, controls, and trends. | E9: Governance forums actively shape strategy, priorities, and resourcing.
C10: Actions are recorded but follow-through is inconsistent. | D10: Action tracking and closure are becoming more disciplined and visible. | E10: Decisions are transparent, well documented, and clearly linked to risk information.
C11: Information from the frontline rarely meaningfully influences leadership decisions. | D11: There is growing visibility of frontline issues at leadership level. | E11: Two-way flow of safety information is strong, timely, and trusted.
A12: LEGAL & RISK GOVERNANCE | B12: Intent: Legal duties and risk boundaries are systematically translated into practical controls and decision rules, ensuring that governance is defensible, consistent, and aligned to the organisation’s tolerance for risk. 3.1 Translation of Legal Duties Currency and relevance of the legal register Clear mapping of legal duties to controls and roles Use of legal requirements in risk assessments and procedures Systematic updates when laws or standards change 3.2 Risk Appetite and Decision Boundaries Existence and clarity of a documented risk appetite Consistent application of risk boundaries in decisions Alignment between risk appetite, approvals, and planning Leadership intervention when risk boundaries are approached | C12: A legal register exists, but is treated mainly as a compliance artefact rather than an operational tool. | D12: The legal register is current and more clearly linked to key controls and accountable roles. | E12: The legal register is a live governance tool that actively shapes control design and decision-making.
C13: Legal duties are not consistently reflected in risk assessments or procedures. | D13: High-risk planning more regularly considers relevant legal requirements. | E13: Legal duties are embedded into risk assessments, permits, and critical controls as standard practice.
C14: Risk appetite is largely implicit and decisions are often driven by urgency or experience. | D14: A documented risk appetite exists and is increasingly referenced in approvals and planning. | E14: Risk appetite is fully operationalised and consistently guides decisions across the business.
C15: Similar risks are often treated differently depending on who is involved. | D15: There is growing consistency in how comparable risks are managed. | E15: Risk decisions are principled, transparent, and defensible to regulators, clients, and stakeholders.
C16: Updates to laws or standards are reactive. | D16: Legal changes trigger some procedural or control updates. | E16: Legal changes automatically trigger systematic reviews of controls, procedures, and training.
A17: ESCALATION, PSYCHOLOGICAL SAFETY & LEARNING INTO GOVERNANCE | B17: Intent: The organisation actively encourages and protects upward flow of risk information, fosters psychological safety, and ensures that learning from incidents, near misses, and operational experience meaningfully reshapes leadership decisions and system design. 4.1 Escalation Pathways and Speak-Up Clarity and accessibility of speak-up and escalation routes Defined response timeframes and feedback loops Protection from retaliation when concerns are raised Evidence that issues raised lead to visible action 4.2 Psychological Safety Leadership behaviours that invite challenge and bad news Quality of dialogue in meetings and decision forums Absence of blame and fear of consequences for speaking up Evidence that constructive dissent is valued and acted upon 4.3 Learning Feeding Back into Governance Quality and depth of incident investigations Evidence that learning leads to system or governance changes Sharing of lessons beyond the immediate site or team Continuous refinement of decision rules, controls, or structures | C17: Formal speak-up channels exist, but awareness and trust are uneven. | D17: Clear escalation routes are understood across most teams, with improving response times. | E17: Escalation pathways are clear, trusted, and used consistently by employees and contractors.
C18: People may raise issues, but feedback and visible outcomes are inconsistent. | D18: Leaders more regularly close the loop with those who speak up. | E18: Feedback loops are systematic, visible, and used to improve the system.
C19: Psychological safety is emerging, but challenge still feels uncomfortable. | D19: Leaders increasingly invite dissent and constructive challenge. | E19: Healthy debate is routine, and leaders actively seek out dissenting views.
C20: Investigations occur after serious events, but learning often stays local. | D20: Investigations more often identify systemic contributors, not just immediate causes. | E20: Investigations routinely examine leadership decisions, governance, and system design.
C21: Corrective actions focus on immediate fixes rather than systemic change. | D21: Learning more regularly leads to updates in controls or procedures. | E21: Learning consistently drives changes to governance, decision rights, and risk boundaries.
C22: The system feels reactive rather than proactive. | D22: Improvement is becoming more structured, though still uneven. | E22: The system is self-reinforcing and continuously evolving based on real operational experience.

Sheet Assessment Prompts
B1: Intent and Criteria to Assess | C1: Process Question Examples Use when conducting field assessments or desktop assessments with workers and leaders. | D1: People Question Examples Use when conducting field assessments or desktop assessments with workers and leaders. | E1: System-Based Queries/ Observations Use to validate use, quality and consistent use of systems to achieve governance objectives. | F1: Symbols/ Behaviours Observations Use to identify symbols or behaviours within the workplace during the assessment that indicate performance.
A2: LEADERSHIP & ACCOUNTABILITY | B2: 1.1 Leadership Intent and Expectations Leadership clearly defines what safety means for the organisation and translates that intent into consistent expectations for how work is planned and decided. Focus Areas Clarity and consistency of leadership safety intent Translation of intent into roles, expectations and decisions Shared understanding of safety intent across leadership layers Visible alignment between what leaders say and what they do | C2: Clarity and consistency of leadership safety intent How is leadership’s safety intent described in your organisation? Where would I find that intent written down, and how often is it reviewed? Has leadership’s safety intent changed in recent years, and if so, why? How is leadership intent communicated to different parts of the business? Translation of intent into roles, expectations, and decisions How are safety expectations built into leader or supervisor roles? Where are those expectations documented, for example in role descriptions or performance objectives? How do planning processes take leadership’s safety intent into account? When there is a conflict between schedule, cost, and safety, how is that typically resolved in your processes? Shared understanding across leadership layers How do you make sure leaders at different levels have a common understanding of safety priorities? Are there forums or routines where leaders align on safety expectations? If yes, how do these work? Alignment between words and actions How do leaders demonstrate their safety intent through day-to-day decisions? What mechanisms exist to check whether leadership behaviour aligns with stated safety intent? | D2: How leaders and workers interpret intent If I asked five leaders what “good safety” means here, how similar do you think their answers would be? In your view, what do senior leaders care about most when things get busy or under pressure? How intent shows up in real work Can you tell me about a recent situation where safety and productivity were in tension? How was that handled? When plans change at short notice, how clear is it what leaders expect from a safety perspective? Consistency across teams and sites Do you think safety expectations are applied the same way across different teams or shifts? Why or why not? Are there examples where one leader handles risk very differently to another? What does that look like? How people feel about leadership intent Do people generally feel confident they understand what leadership expects when it comes to safety? Do you feel supported by leadership when you prioritise safety, even if it slows work down? | E2: Clear articulation of safety intent A documented leadership safety intent, vision, or statement that is more than generic “safety first” language. Evidence that this intent has been discussed and refined by leadership, not simply copied from another organisation. Records of leadership conversations about what “good safety” actually means for this business. Translation into roles and decision-making Role descriptions, KPIs, or performance expectations that explicitly reference safety leadership behaviours, not just compliance. Evidence that safety intent is considered in planning documents, risk assessments, or project decisions. Examples where leadership intent has influenced a real operational decision, especially where cost or schedule was impacted. Leadership alignment mechanisms Leadership forums or routines where safety intent is discussed, aligned, or reinforced. Evidence of consistent messaging across leadership layers, such as common talking points, shared priorities, or aligned strategies. Induction or onboarding materials that explain leadership expectations around safety. Mechanisms to check alignment between words and actions Site walk programs, leader field engagement plans, or structured safety interactions. Feedback mechanisms where workers can comment on leadership behaviours. Evidence that leadership behaviour is reviewed or reflected upon, not just performance metrics. | F2: What is displayed on walls Are safety posters generic, or do they reflect the organisation’s specific risks and priorities? Do leadership messages feel authentic or corporate and disconnected? Are operational priorities (production, cost, schedule) more visually dominant than safety messaging? What leaders talk about when they are unscripted In casual conversations, do leaders naturally reference safety, risk, or lessons learned? Or do they default to schedule, output, and performance only? What gets celebrated or recognised Are people recognised for raising concerns, stopping work, or preventing incidents? Or is recognition mostly for productivity, efficiency, or meeting targets? During site walks or meetings Do leaders ask thoughtful questions about risk, controls, and decision-making? Do they genuinely listen, or do they lecture and move on? Do they challenge unsafe conditions, or walk past them? Under pressure or time constraints When schedules are tight, do leaders still prioritise safety conversations? Do they visibly support slowing down or stopping work if risks are unclear? Across different leadership levels Do frontline supervisors, middle managers, and senior leaders describe safety in similar ways? Or do you hear different interpretations depending on who you speak to? Alignment between words and actions If leaders say “safety is our priority,” do their decisions actually reflect that? For example, do they allocate time, people, and resources to safety activities?
B3: 1.2 Leadership Accountability for Outcomes Leadership is explicitly accountable for safety outcomes and the performance of the safety system, not just compliance or incident rates. Focus Areas Formal accountability for safety in leadership performance measures Ownership of system performance and critical control health Leadership response to incidents, risk and system failures Consistency and fairness in how accountability is applied | C3: Formal accountability mechanisms How is safety built into leadership performance reviews or objectives? Beyond injuries, what safety performance measures are leaders held accountable for? How are leaders held accountable for critical controls or major risks? Are there formal consequences when safety performance or system performance is poor? If yes, how does that work? Ownership of system performance How do leaders monitor the health of critical controls in your business? What regular reviews or dashboards do leaders use to understand safety system performance? How are recurring safety issues escalated and addressed at leadership level? Leadership response to incidents and failures When significant incidents or near misses occur, what is the typical leadership response? How are leadership decisions reviewed following serious events? What usually changes at a leadership or system level after a major incident? Consistency and fairness Are safety accountabilities applied consistently across different leaders and business units? How does the organisation avoid blame-focused responses after incidents? | D3: How accountability feels in practice Do you feel leaders genuinely own safety outcomes, or is it mostly pushed down to supervisors and workers? When things go wrong, do people feel the system is examined, or mainly individual behaviour? Accountability for system performance, not just incidents Have you seen examples where leaders took responsibility for system weaknesses rather than blaming individuals? Are leaders more focused on injury numbers or on whether controls are actually working? Leadership behaviour after incidents Can you describe how leaders responded to the last serious incident or near miss? Did that response lead to meaningful changes, or mostly paperwork and reminders? Fairness and consistency In your experience, are safety consequences applied fairly across different levels of leadership? Would you say accountability feels constructive and improvement-focused, or reactive and punitive? | E3: Formal accountability mechanisms Leadership performance frameworks that include safety leadership behaviours, not just incident statistics. Evidence that leaders are assessed on critical control health, quality of investigations, effectiveness of corrective actions, and engagement with frontline workers. Clear documentation showing how safety outcomes influence performance reviews, bonuses, or development plans. Ownership of system performance Dashboards or reports that track system health rather than only injuries, such as control verification, audit trends, and near-miss learning. Regular leadership reviews that focus on whether controls are effective, not just whether incidents occurred. Named leaders with clear accountability for specific high-risk controls or major risk areas. Leadership response to incidents, risk, and system failures Records showing that after significant events, leadership examined decision-making, governance, resourcing, and capability — not only frontline behaviour. Evidence that systemic contributors are identified and addressed in investigation outputs. Documented leadership actions following major incidents that go beyond procedural updates. Consistency and fairness in accountability Clear differentiation between honest error, system failure, and reckless behaviour in investigation outcomes. Evidence that accountability is applied consistently across leadership layers, not only to frontline workers. Investigation reports and reviews that emphasise learning and system improvement rather than blame. | F3: What is discussed in leadership meetings Are meetings dominated by injury numbers, or do leaders actively discuss risk, controls, and system performance? Do leaders ask questions like “what does this tell us about our system” rather than “who was responsible”? What is visible after incidents Do you see tangible changes to governance, decision rules, or resourcing, or mainly updated paperwork and reminders? Are leadership behaviours or decisions visibly adjusted following serious events? How accountability is framed in language Do leaders talk about “our system failed” rather than “they made a mistake”? Is learning and improvement the dominant tone, or is there a subtle search for someone to blame? When things go wrong Do leaders visibly take responsibility, or do they distance themselves from the issue? Are they curious and reflective, or defensive and reactive? In discussions about risk and controls Do leaders actively seek evidence that critical controls are working in practice? Or do they assume everything is fine because there were no injuries? Across leadership layers Do senior leaders hold middle managers accountable for safety leadership, not just delivery of work? Do middle managers feel supported to address system issues, or pressured to “make problems go away”? In everyday decision-making Do leaders allocate time, people, and budget to safety activities before incidents occur? Or does meaningful investment in safety only happen after something goes wrong?
A4: DECISION RIGHTS & GOVERNANCE STRUCTURE | B4: Intent and Criteria to Assess | C4: Assessment Question Examples Use when conducting field assessments or desktop assessments with workers and leaders. | D4: People Question Examples Use when conducting field assessments or desktop assessments with workers and leaders. | E4: System-Based Queries/ Observations Use to validate use, quality and consistent use of systems to achieve governance objectives. | F4: Symbols/ Behaviours Observations Use to identify symbols or behaviours within the workplace during the assessment that indicate performance.
B5: 2.1 Decision Rights for High-Risk Work Decision rights for high-risk work are clear, consistently applied, and understood across all levels, ensuring timely, risk-informed decisions and effective stop-work authority. Focus Areas Clarity of approval, escalation, and stop-work authority Consistent application of decision rules in practice Alignment between documented decision rights and real decisions Functionality of escalation pathways under pressure | C5: Clarity of approval, escalation, and stop-work authority How are decision rights for high-risk work described in your organisation? Where would I find these decision rights documented? How are approval levels determined for different types of risk? How is stop-work authority defined in your procedures or policies? Consistent application of decision rules How do you ensure decision rules are applied the same way across teams or sites? Are there standard thresholds or criteria that trigger escalation or review? How are contractors included in your decision-rights arrangements? Alignment between documented decision rights and real decisions How do you check that decisions made in the field align with what is written in your decision-rights documents? When decisions deviate from the documented process, how is that managed or reviewed? Functionality of escalation pathways under pressure How are escalation pathways expected to work when schedules or budgets are under pressure? Are there any formal triggers that require mandatory escalation? If so, what are they? How do you capture and review escalations after they occur? | D5: How clear decision rights feel in practice If you had to make a high-risk decision tomorrow, how confident would you feel about who has the final say? Why? Do people generally agree on who should be involved in high-risk decisions, or does it vary? Real-world use of stop-work authority Can you tell me about a time when work was stopped due to safety concerns? What happened? How comfortable do people feel using stop-work authority? What makes it easier or harder? How decisions play out under pressure When deadlines are tight, how does that affect safety decision-making? In your experience, does escalation happen early or only when things are already going wrong? Alignment between documents and reality Do the formal decision-rights documents reflect how decisions actually get made day to day? Why or why not? Are there situations where people rely more on relationships than formal processes to get decisions made? | E5: Clear articulation of decision rights A documented decision-rights framework that defines who can approve, escalate, pause, or stop high-risk work. Clear thresholds that trigger escalation, additional review, or mandatory leadership involvement. Defined stop-work authority that applies to all workers, supervisors, and contractors. Consistent application of decision rules Standard criteria or decision rules that are applied across teams, sites, and shifts. Evidence that contractors are explicitly included in decision-rights arrangements. Records showing when and why decisions were escalated or stopped. Alignment between documented decision rights and real decisions Mechanisms that check whether field decisions align with documented processes, such as audits, reviews, or case studies. A clear way to document and review deviations from formal decision rules. Evidence that learnings from deviations are used to refine the decision framework. Functionality under pressure Pre-defined escalation pathways that operate under schedule, commercial, or operational pressure. Mandatory escalation triggers for specific high-risk scenarios. Post-event reviews that analyse whether escalation pathways worked as intended. | F5: How decision rights are visible in everyday work Are decision-rights diagrams, flowcharts, or escalation maps visibly displayed and actually referenced? Do people on the frontline recognise these artefacts, or are they purely “head office documents”? Use of stop-work in practice Do you see examples where work has genuinely been stopped due to safety concerns? Is stopping work treated as a failure, a nuisance, or a professional decision? Behaviour under pressure When deadlines are tight, do leaders and supervisors still pause, consult, or escalate? Or do decisions get pushed down, rushed, or informally “worked around”? Who actually makes decisions Do decisions follow formal lines of authority, or do relationships and hierarchy override them? Are the same people consistently pulled into high-risk decisions, or does it vary? Consistency across teams and sites Do different crews describe decision rights in similar ways? Or does every team seem to operate by its own unwritten rules? Confidence and clarity in the field Do workers and supervisors appear confident about who has the final say? Or do you hear hesitation, confusion, or statements like “it depends who’s on shift”? Reaction to escalation When someone escalates, do leaders respond promptly and constructively? Or do people appear reluctant to escalate because it causes friction or delays?
B6: 2.2 Governance Forums and Structure A clear and effective governance structure enables purposeful safety decision-making, oversight, and accountability across the organisation. Focus Areas Clarity of governance structure, roles, and forums Quality and purposefulness of safety meetings and reviews Decision-making, action tracking, and follow-through Flow of safety information between frontline and leadership | C6: Clarity of governance structure, roles, and forums How is your safety governance structure organised? What are the main safety forums or committees, and what are their purposes? How often do these forums meet, and who is expected to attend? How are roles and responsibilities within these forums defined? Quality and purposefulness of meetings and reviews What is typically covered in your safety meetings or management reviews? How do you decide what issues are discussed at each forum? How do you ensure meetings focus on real risk rather than just reporting numbers? Decision-making, action tracking, and follow-through How are decisions recorded and communicated from governance forums? How are actions assigned, tracked, and closed out? How do you know whether actions have actually made a difference? Flow of safety information between frontline and leadership How do frontline concerns or learnings get elevated to leadership forums? How do leaders share decisions or outcomes back to the workforce? Are there formal mechanisms for two-way communication on safety issues? | D6: How effective governance feels in practice Do people see safety forums as useful or more of a formality? Why? When issues are raised in these forums, do people feel they are genuinely heard? Quality of conversations In your experience, do safety meetings tend to focus more on numbers or on real risks? Are difficult or uncomfortable safety topics openly discussed, or avoided? Action and follow-through When actions are raised in meetings, do they usually get resolved? Can you give an example? Have you seen situations where the same issues keep coming up without real change? Frontline to leadership connection Do you feel there is a good flow of safety information between workers and leadership? Why or why not? When frontline issues are raised, do you usually see visible outcomes or feedback? | E6: Clear governance structure and roles A documented governance structure that clearly shows safety forums, committees, and accountabilities. Defined purpose, membership, and decision authority for each forum. Regular meeting cadence that aligns with risk and operational tempo. Purposeful safety meetings Agendas that prioritise high-risk issues, critical controls, and systemic trends rather than only incident counts. Evidence that meetings are used to make real decisions, not just report information. Clear records of discussions, decisions, and rationale. Decision-making and follow-through Formal mechanisms for assigning, tracking, and closing actions. Evidence that actions are reviewed for effectiveness, not just completion. A clear link between governance decisions and changes in operations, controls, or resources. Frontline to leadership information flow Formal pathways for frontline concerns, insights, and learning to reach leadership forums. Mechanisms for leaders to communicate outcomes and decisions back to the workforce. Evidence that feedback loops operate in both directions, not just top-down. | F6: What is visible in governance artefacts Do minutes clearly show risk-based discussions and decisions, or mostly slide decks and metrics? Are actions specific, owned, and time-bound, or vague and recycled from previous meetings? Tone and quality of meetings Do meetings feel purposeful, or like a box-ticking exercise? Are difficult or uncomfortable safety topics openly discussed, or subtly avoided? How decisions are experienced When decisions are made in governance forums, do they actually change what happens in the field? Or do frontline teams experience little difference after major reviews? Action fatigue or action impact Do you see repeated actions about the same issues without real change? Or do actions lead to visible improvements in controls, resources, or practices? Connection between frontline and leadership Do workers feel their concerns reach leadership in a meaningful way? Do leaders reference real frontline issues in their discussions, or only high-level reports? Leadership engagement with governance Do senior leaders actively participate, ask questions, and challenge assumptions? Or do they attend but remain largely passive? Transparency and trust Are governance decisions communicated clearly and honestly to the workforce? Do people feel decisions are made fairly and based on risk, not politics or convenience?
A7: LEGAL & RISK GOVERNANCE | B7: Intent and Criteria to Assess | C7: Assessment Question Examples Use when conducting field assessments or desktop assessments with workers and leaders. | D7: People Question Examples Use when conducting field assessments or desktop assessments with workers and leaders. | E7: System-Based Queries/ Observations Use to validate use, quality and consistent use of systems to achieve governance objectives. | F7: Symbols/ Behaviours Observations Use to identify symbols or behaviours within the workplace during the assessment that indicate performance.
B8: 3.1 Translation of Legal Duties Legal duties are systematically translated into practical controls and accountabilities so governance is defensible and operationally meaningful. Focus Areas Currency and relevance of the legal register Clear mapping of legal duties to controls and roles Use of legal requirements in risk assessments and procedures Systematic updates when laws or standards change | C8: Currency and relevance of the legal register How do you keep your legal register up to date? Who is responsible for maintaining it, and how often is it reviewed? How do you decide which laws, codes or standards are most relevant to your operations? How do you make sure the register reflects what you actually do, not just generic legislation? Mapping legal duties to controls and roles How are legal duties translated into your controls, procedures or standards? Where can I see the link between a specific legal duty and the controls that manage it? How do you make clear who is accountable for meeting key legal duties? How are these accountabilities communicated to leaders and supervisors? Use of legal requirements in risk assessments and procedures How are legal requirements considered when you do risk assessments or SWMS? Can you show me an example where a legal requirement clearly shaped how a task is controlled? How do you avoid legal requirements becoming just “cut and paste” text in documents? Systematic updates when laws change What happens in your system when legislation or standards change? How do you identify which procedures, controls or roles need updating? How do you verify that changes have actually been implemented, not just documented? | D8: How leaders and workers understand legal duties If I asked a supervisor what their key legal duties are, how confident are you they could explain them? Do people generally see legal requirements as practical guidance or as paperwork? Why? How legal duties shape real decisions Can you describe a time when a legal duty influenced a real operational decision? When there is pressure to get work done, do legal requirements still meaningfully shape decisions? How? Ownership and clarity Do leaders feel clear about what they are legally accountable for, or is it often seen as “HSE’s job”? Do workers understand why certain controls exist in relation to legal duties, or do they just follow them? | E8: Currency and relevance of the legal register A current legal register that clearly relates to the organisation’s actual activities, plant, and risks rather than a generic list of legislation. Clear ownership for maintaining the register, with defined review cycles and triggers for updates. Evidence that the register has been actively curated, not just periodically refreshed. Mapping legal duties to controls and roles Clear line-of-sight from specific legal duties to critical controls, procedures, and accountable roles. Role descriptions or accountability documents that explicitly reference key legal obligations. Mechanisms that show how legal duties are considered when designing or modifying controls. Use of legal requirements in risk assessments and procedures Risk assessments, SWMS, or work plans that explicitly reference relevant legal requirements where they are material to the risk. Procedures that translate legal duties into practical, operational steps rather than copying legislative text. Evidence that legal considerations influence how work is actually planned and authorised. Systematic updates when laws change A defined process for identifying changes in legislation or standards and assessing their impact. Documented reviews showing which controls, procedures, or roles were updated as a result. Verification activities that confirm changes were implemented in practice, not only on paper. | F8: How legal duties are talked about Do leaders and supervisors describe legal duties as practical guidance or as “paperwork for HSE”? Is there a shared language that links legal duties to real risks and controls? Visibility of legal influence in documents When reviewing procedures or risk assessments, do legal references feel purposeful or pasted in? Are legal duties clearly connected to why certain controls exist? Ownership and clarity in the field Do supervisors appear confident about their key legal accountabilities, or do they defer to HSE? Do workers understand the “why” behind legally driven controls, or do they just follow rules? Response to legal change When laws or standards change, do you see visible updates in procedures, training, or controls? Or do changes appear slow, reactive, or superficial? Alignment between words and reality If leaders say “we are legally compliant,” do field practices actually reflect that? Are there examples where legal obligations shaped real operational decisions, especially under pressure? Depth versus surface compliance Do you see evidence of thoughtful interpretation of legal duties, or mainly cut-and-paste compliance? Are legal requirements used to strengthen risk management, or treated as a minimum hurdle?
B9: 3.2 Risk Appetite and Decision Boundaries Clear and shared risk boundaries guide consistent, defensible decision-making for routine and high-risk work. Focus Areas Existence and clarity of a documented risk appetite Consistent application of risk boundaries in decisions Alignment between risk appetite, approvals, and planning Leadership intervention when risk boundaries are approached | C9: Existence and clarity of risk appetite Does your organisation have a documented risk appetite statement? How would you describe your risk appetite in simple terms? Where is it documented, and who is expected to use it? How often is it reviewed or updated? Application of risk boundaries in decisions How is risk appetite used in planning high-risk work? Are there clear thresholds that trigger escalation or additional approval? How are these thresholds defined and communicated? How do you make sure different teams apply these boundaries consistently? Alignment with approvals and planning How do approval processes reflect your stated risk appetite? When project timelines or budgets are tight, how do you ensure risk boundaries are still respected? How do you handle situations where commercial pressure conflicts with risk boundaries? Leadership intervention near boundaries What happens when work approaches the edge of your risk tolerance? How do leaders get visibility of these situations? Are there formal triggers that require leadership involvement? | D9: Shared understanding of risk appetite If I asked five leaders what your risk appetite is, how similar do you think their answers would be? Do supervisors and frontline teams understand where the “lines in the sand” are? Why or why not? How risk boundaries play out in real work Can you give an example where risk appetite clearly shaped a decision in the field? Have you ever seen work proceed even when it felt close to or beyond your risk boundaries? What happened? Consistency and fairness Do you feel similar risks are treated the same way across teams or projects? Are decisions about risk boundaries influenced more by the situation, the leader, or the rules? Leadership behaviour near risk boundaries When risks escalate, do leaders tend to step in early or only after problems arise? Do leaders support teams who stop work or slow down due to risk concerns? | E9: Existence and clarity of risk appetite A documented risk appetite statement that is specific, operational, and relevant to the organisation’s high-risk activities. Clear definitions of what risks are acceptable, tolerable, and unacceptable. Regular review records showing that risk appetite is actively maintained rather than static. Application of risk boundaries in decisions Defined thresholds that trigger escalation, additional controls, or leadership approval. Evidence that risk appetite is referenced in planning, permits, and high-risk work decisions. Mechanisms to promote consistency in how risk boundaries are applied across teams or sites. Alignment with approvals and planning Approval processes that explicitly reflect the stated risk appetite. Clear links between risk appetite, project planning, and resource allocation. Documented examples where risk boundaries influenced scope, sequencing, or control selection. Leadership intervention near boundaries Defined triggers that require leadership involvement when risk approaches agreed limits. Records showing leadership engagement in high-risk or boundary cases. Post-event reviews that assess whether interventions were timely and effective. | F9: How risk appetite is described in everyday language Do leaders and supervisors talk about risk boundaries in similar, practical terms? Or do descriptions vary widely depending on who you speak to? Visibility of risk boundaries in work Are risk thresholds clearly understood by frontline teams, or do they feel abstract? Do workers know when a situation should be escalated versus handled locally? Consistency across teams and sites Do similar risks get treated in similar ways across different crews or projects? Or does the approach depend more on the leader, location, or schedule? Behaviour near risk boundaries When work approaches the edge of tolerance, do leaders step in early or only after issues arise? Do teams feel supported when they slow down or stop work due to risk concerns? Pressure versus principle Under commercial or schedule pressure, do decisions still respect risk boundaries? Or do you see informal “workarounds” that quietly erode the stated risk appetite? Alignment between documents and reality Does what is written in the risk appetite statement match how decisions are actually made? Are there examples where stated boundaries were genuinely tested and upheld? Learning from boundary cases When risks were close to limits, did the organisation adjust decision rules or controls? Or did the same situations reoccur without meaningful change?
A10: ESCALATION, PSYCHOLOGICAL SAFETY & LEARNING INTO GOVERNANCE | B10: Intent and Criteria to Assess | C10: Assessment Question Examples Use when conducting field assessments or desktop assessments with workers and leaders. | D10: People Question Examples Use when conducting field assessments or desktop assessments with workers and leaders. | E10: System-Based Queries/ Observations Use to validate use, quality and consistent use of systems to achieve governance objectives. | F10: Symbols/ Behaviours Observations Use to identify symbols or behaviours within the workplace during the assessment that indicate performance.
B11: 4.1 Escalation Pathways and Speak-Up Clear, trusted, and accessible escalation pathways enable anyone to raise safety concerns without fear and with timely response. Focus Areas Clarity and accessibility of speak-up and escalation routes Defined response timeframes and feedback loops Protection from retaliation when concerns are raised Evidence that issues raised lead to visible action | C11: Clarity and accessibility of speak-up routes What formal ways can people use to raise a safety concern in your organisation? Where are these options explained or displayed for workers and contractors? Are there different routes depending on the type or severity of the concern? How? How are new starters or contractors made aware of these pathways? Response timeframes and feedback loops Are there defined timeframes for responding to safety concerns? What are they? How do people who raise issues know what has happened with their concern? How is feedback recorded and tracked? How do you monitor whether responses are happening quickly enough? Protection from retaliation What formal protections exist to prevent retaliation when someone raises a concern? How are leaders trained or guided to handle speak-up appropriately? How would someone report retaliation if it occurred? Evidence of action How do you demonstrate that concerns raised lead to real action? Where would I see examples of issues raised and what changed as a result? How are recurring issues reviewed to prevent them happening again? | D11: Trust and accessibility If someone on your team had a serious safety concern, how likely are they to raise it? Why? Do people feel it is easier to speak up formally or informally? What drives that? Experience of response and feedback Can you think of a time when someone raised a concern? What happened next? Do people generally feel they get meaningful feedback after speaking up? Fear of retaliation Do people worry about negative consequences if they raise safety issues? Why or why not? Have you ever seen or heard of retaliation for speaking up? What happened? Impact of escalation When concerns are raised, do you usually see visible changes, or does it feel like nothing happens? What makes people more or less willing to escalate issues here? | E11: Clarity and accessibility of escalation routes Clearly documented speak-up and escalation pathways that are simple, visible, and available to employees and contractors. Multiple options for raising concerns, including formal and informal routes. Evidence that pathways are explained during induction, onboarding, and refresher training. Defined response timeframes and feedback loops Documented timeframes for acknowledging and responding to concerns. A tracking system that records issues raised, actions taken, and status. Mechanisms to provide feedback to the person who raised the issue, even when outcomes take time. Protection from retaliation Formal policies or procedures that explicitly prohibit retaliation for speaking up. Clear processes for reporting and investigating retaliation. Evidence that leaders are trained or guided on how to respond appropriately to concerns. Evidence of action from issues raised Records showing that concerns have led to tangible changes in controls, processes, or behaviours. Review processes that analyse recurring issues to identify systemic causes. Visible communication back to the workforce about what changed because people spoke up. | F11: Visibility of speak-up in the environment Are speak-up posters, contact details, or QR codes clearly displayed where people actually work? Do they look current and used, or faded and ignored? How people talk about escalation Do workers describe speak-up as a normal part of work, or something you only use as a last resort? Do people refer to formal channels, or mainly rely on personal relationships? Experience of response and feedback When someone raises an issue, do they feel kept in the loop, or left in the dark? Do people cite examples where speaking up actually led to change? Fear or comfort in raising concerns Do people appear relaxed discussing safety issues openly, or cautious about what they say? Do you hear stories of retaliation, or reassurance that it would not happen? Behaviour when concerns arise When risks are raised, do leaders respond promptly and constructively? Or do people appear reluctant to escalate because it causes tension, delay, or inconvenience? Pattern of issues raised Are concerns treated as isolated problems, or as signals of deeper system issues? Do you see evidence that leadership actively seeks out issues rather than waiting for them to be reported?
B12: 4.2 Psychological Safety Leaders create conditions where people feel safe to surface risk, challenge decisions, and speak openly about problems. Focus Areas Leadership behaviours that invite challenge and bad news Quality of dialogue in meetings and decision forums Absence of blame and fear of consequences for speaking up Evidence that constructive dissent is valued and acted upon | C12: Leadership behaviours that invite challenge How do leaders formally encourage people to speak up or challenge decisions? Are there any structured forums designed specifically for open discussion or learning? How are leaders supported or trained to build psychological safety? Quality of dialogue in meetings How are safety discussions typically run in meetings? Are difficult or uncomfortable topics included in agendas? How? How are differing opinions handled in decision forums? Absence of blame What guidance exists on how incidents or mistakes should be handled? How does the organisation differentiate between honest error and reckless behaviour? How are investigation findings communicated to avoid blame? Valuing constructive dissent Are there examples where people who challenged decisions were recognised or thanked? How do leaders signal that dissent is welcome rather than unwelcome? | D12: Comfort in speaking up Do people generally feel safe raising concerns in front of their leader or peers? Why or why not? Are there topics that feel “unsafe” to discuss openly? What makes them that way? Real conversations vs polite compliance In meetings, do people tend to speak honestly or mainly say what they think leaders want to hear? Can you recall a time when someone disagreed with a decision? How was it handled? Leadership reactions How do leaders typically respond when someone brings bad news or a problem? Do leaders tend to get defensive, curious, or solution-focused? Culture and trust Do people feel that raising issues leads to learning or punishment? If you made a mistake tomorrow, how confident are you that it would be treated fairly? What would make it easier for people to speak up here? | E12: Leadership behaviours that invite challenge Formal guidance or expectations for leaders to encourage questions, dissent, and bad news. Structured forums or routines designed for open discussion and reflection rather than reporting only. Training or development programs that support leaders to build psychological safety. Quality of dialogue in meetings Agendas that include space for discussion of risks, uncertainties, and differing perspectives. Evidence that difficult or uncomfortable topics are intentionally brought into the conversation. Clear norms about respectful debate and constructive challenge. Absence of blame Investigation frameworks or policies that emphasise learning over punishment. Clear distinction between honest error, system failure, and reckless behaviour. Communication practices that avoid naming or shaming individuals in incident reviews. Valuing constructive dissent Examples where people who challenged decisions were thanked, supported, or recognised. Mechanisms for capturing and considering alternative viewpoints before major decisions. Leadership behaviours that visibly reward speaking up rather than penalising it. | F12: How safe it feels to speak Do people appear comfortable raising concerns in front of their leader and peers? Are there topics that feel “off limits” or sensitive? Real conversations versus polite compliance In meetings, do people speak honestly, or mainly agree with leaders? When someone disagrees, is it handled constructively or shut down? Leadership reactions to bad news Do leaders respond with curiosity and questions, or defensiveness and frustration? Do they listen fully, or interrupt and redirect the conversation? Tone after mistakes or incidents When errors occur, is the focus on understanding and learning, or finding someone to blame? Do people feel safer to report near misses and mistakes, or inclined to hide them? Trust and fairness If someone made a mistake tomorrow, would they expect a fair response? Do people believe that speaking up leads to improvement rather than punishment? Everyday interactions Do leaders regularly ask for input and alternative views? Do you see workers proactively raising risks without being prompted?
B13: 4.3 Learning Feeding Back into Governance Insights from incidents, near misses, and operational experience actively reshape leadership decisions and system design. Focus Areas Quality and depth of incident investigations Evidence that learning leads to system or governance changes Sharing of lessons beyond the immediate site or team Continuous refinement of decision rules, controls, or structures | C13: Quality and depth of investigations How are serious incidents and near misses investigated? Who is involved in investigations, and how are they selected? How do you ensure investigations look beyond immediate causes to systemic factors? How is leadership involved in reviewing investigation findings? Learning leading to system change How are investigation learnings translated into changes in controls, procedures, or governance? Where would I see examples of leadership-level changes following an incident? How do you check whether changes actually reduced risk? Sharing lessons beyond one site How are lessons learned shared across teams, sites, or projects? Are there formal forums, bulletins, or platforms for sharing learning? How do you ensure contractors or partner organisations receive relevant lessons? Continuous refinement How are decision rules, risk boundaries, or governance structures reviewed over time? What triggers a review of these elements? How do you capture and use operational experience to improve the system? | D13: Perception of investigations Do people see investigations as fair and focused on learning, or mainly on blame? Why? After incidents, do people feel the “real” issues are addressed or just the obvious ones? Visibility of learning Can you think of a recent example where learning led to real change? What changed? Do workers generally know what has been learned from past incidents? Impact on leadership and governance Have you seen leadership change how they make decisions because of an incident or near miss? Do people feel the system gets better over time, or do the same issues keep coming back? Engagement with learning Are people encouraged to share near misses or lessons from everyday work? Do you feel your experience on the ground actually influences how the system is designed or governed? | E13: Quality and depth of investigations Defined investigation processes that look beyond immediate causes to systemic contributors. Involvement of relevant leaders, subject matter experts, and frontline workers in investigations. Clear documentation of findings, including governance, decision-making, and control effectiveness. Learning leading to system change Mechanisms that translate investigation learnings into changes in controls, procedures, or governance. Evidence of leadership-level actions following significant incidents or near misses. Processes to verify whether implemented changes actually reduced risk in practice. Sharing lessons beyond one site Formal platforms, forums, or bulletins for sharing lessons across teams, sites, or projects. Evidence that contractors or partners receive relevant learnings where applicable. Records showing that lessons are not only shared but discussed and understood. Continuous refinement of governance Regular reviews of decision rules, risk boundaries, and governance structures. Clear triggers for reviewing these elements, such as incidents, trends, or audits. Mechanisms to capture operational experience and feed it into system design. | F13: How investigations are perceived Do people see investigations as fair and focused on learning, or mainly about blame? After incidents, do workers feel the “real issues” were addressed? Visibility of learning Can people readily point to examples where learning led to real change? Are lessons from past events visible in current procedures, training, or practices? Impact on leadership and governance Have you seen leadership change how they make decisions because of an incident or near miss? Do people feel the system gets better over time, or do the same issues keep repeating? Engagement with near misses and experience Are people encouraged to report near misses and small signals of risk? Do frontline insights genuinely influence how controls or governance are designed? Connection between events and system change When incidents occur, do changes focus only on local fixes, or on broader system improvement? Do you see evidence that decision rules or risk boundaries have evolved based on learning? Learning culture Does the organisation talk about learning from its own experience and from industry? Is there a visible “hunger to learn,” or does learning feel like a compliance activity?

Sheet Scoring Requirements
B2: Governance Core Assessment
B3: Scoring Methodology
B5: Step One | C5: Application of the scoring scale
C6: Using the scoring structure and definitions below, the assessor shall determine the maturity score for each assessment criterion based on the operation of the management system in practice. Scores reflect how the system functions, not the quality of documentation in isolation.
B8: Step Two | C8: Progressive maturity logic
C9: The maturity scale is cumulative. To assign a score within the Proactive or Resilient maturity levels, all lower maturity requirements must first be met for that criterion. For example: • A score of 5 cannot be assigned unless the conditions represented at 3 are consistently present. • A score of 8 or 9 requires evidence that Reactive and Proactive system characteristics are both established and sustained. This prevents over-scoring isolated strengths where foundational system elements are missing.
B11: Step Three | C11: Scoring basis and averaging
C12: The score for each criterion shall be based on the typical operating state of the system. Outliers, whether high or low performing areas, must not disproportionately influence the overall maturity score. Where performance varies across teams, sites, or layers, the assessor should apply professional judgement and score based on the most representative system condition.
B14: Step Four | C14: Risk coverage expectation
C15: Assessment and scoring must consider the full spectrum of material risk, including: • health and safety risks resulting in injury • risks with single fatality potential • risks with catastrophic potential involving multiple fatalities The assessor should consider whether the management system provides appropriate governance and decision support across this full risk profile, not only lower-consequence events.
B17: Step Five | C17: Criteria with multiple focus areas
C18: Where a criterion includes multiple focus areas, the assessor should determine an overall position on the 9-point scale based on the collective maturity of those focus areas. Scoring should reflect: • the balance between focus areas • the degree to which weaknesses constrain overall system performance A single strong focus area must not mask broader system gaps.
B20: Scoring Structure
B21: Maturity level | E21: Reactive | F21: Proactive | G21: Resilient
B22: Scoring | E22: 1 2 3 | F22: 4 5 6 | G22: 7 8 9
B24: Scoring Definition
B25: Score * | E25: Consistency | F25: Quality | G25: Sustainability
B26: 1 | C26: 4 | D26: 7 | E26: ü | F26: X | G26: X
B27: 2 | C27: 5 | D27: 8 | E27: ü | F27: ü | G27: X
B28: 3 | C28: 6 | D28: 9 | E28: ü | F28: ü | G28: ü
B29: * The operations score for a criteria is to be based on the average. Outliers (high or low performer) are not to influence overall maturity. X Not completely achieved. Variable. ü Completely achieved
B33: Scoring Definition
B34: System Characteristic | F34: What is being tested?
B35: Consistency | F35: Is the system applied reliably across the organisation and through leadership layers?
B36: Quality | F36: Does the system achieve its intended governance and risk management outcomes?
B37: Sustainability | F37: Is consistent, high-quality performance sustained over time (typically ≥ 6 months)?
B39: Scoring Intent
B40: System Strength | F40: What is being tested?
B41: Reactive | F41: System elements exist or are applied inconsistently. Outcomes depend heavily on individuals and local effort.
B42: Proactive | F42: System elements are consistently applied and generally effective. Governance supports decision-making but may still rely on active oversight.
B43: Resilient | F43: System performance is reliable, embedded, and sustained. Governance adapts based on learning and continues to function under pressure and change.

Sheet Lists
B2: Ratings | C2: Score | E2: Consistency | F2: Quality | G2: Sustainable
B3: RCQS | C3: 3 | E3: C | F3: Q | G3: S
B4: RCXX | C4: 1 | E4: X | F4: X | G4: X
B5: RCQX | C5: 2
B6: PCQS | C6: 6
B7: PCXX | C7: 4
B8: PCQX | C8: 5
B9: RECQS | C9: 9
B10: RECXX | C10: 7
B11: RECQX | C11: 8
B12: RXQS | C12: Invalid
B13: RXXS | C13: Invalid
B14: RCXS | C14: Invalid
B15: PXQS | C15: Invalid
B16: PXXS | C16: Invalid
B17: PCXS | C17: Invalid
B18: REXQS | C18: Invalid
B19: REXXS | C19: Invalid
B20: RECXS | C20: Invalid
